grammarticle/__init__.py
grammarticle/loader.py
grammarticle-1.1.0.dist-info/licenses/LICENSE
grammarticle-1.1.0.dist-info/METADATA
grammarticle-1.1.0.dist-info/WHEEL
grammarticle-1.1.0.dist-info/entry_points.txt
grammarticle-1.1.0.dist-info/top_level.txt
grammarticle-1.1.0.dist-info/RECORD
