Metadata-Version: 2.4
Name: grammarticle
Version: 1.1.0
Summary: Grammarticle spaCy pipeline
Home-page: https://github.com/upunaprosk/grammarticle
Author: upunaprosk
Author-email: 
License: MIT
Classifier: Development Status :: 4 - Beta
Classifier: Intended Audience :: Developers
Classifier: Topic :: Scientific/Engineering :: Artificial Intelligence
Classifier: License :: OSI Approved :: MIT License
Classifier: Programming Language :: Python :: 3.7
Classifier: Programming Language :: Python :: 3.8
Classifier: Programming Language :: Python :: 3.9
Classifier: Programming Language :: Python :: 3.10
Classifier: Operating System :: OS Independent
Requires-Python: >=3.7
License-File: LICENSE
Requires-Dist: spacy<3.9.0,>=3.8.5
Requires-Dist: spacy-transformers<1.4.0,>=1.3.8
Requires-Dist: spacy-huggingface-hub==0.0.10
Dynamic: author
Dynamic: classifier
Dynamic: description
Dynamic: description-content-type
Dynamic: home-page
Dynamic: license
Dynamic: license-file
Dynamic: requires-dist
Dynamic: requires-python
Dynamic: summary
